iamstew_excel_parser/__init__.py
iamstew_excel_parser/xls_parser.py
iamstew_excel_parser/xlsx_parser.py
iamstew_excel_parser-0.0.3.dist-info/LICENSE
iamstew_excel_parser-0.0.3.dist-info/METADATA
iamstew_excel_parser-0.0.3.dist-info/WHEEL
iamstew_excel_parser-0.0.3.dist-info/top_level.txt
iamstew_excel_parser-0.0.3.dist-info/RECORD
