Metadata-Version: 2.1
Name: iamstew-excel-parser
Version: 0.0.3
Summary: This is module helps to parse xls and xlsx files
Home-page: https://github.com/iamstew/excel-parser
Author: iamstew
Author-email: kakylya_ija@bk.ru
Project-URL: GitHub, https://github.com/iamstew/excel-parser
Keywords: xls xlsx excel parser
Classifier: Programming Language :: Python :: 3.11
Classifier: License :: OSI Approved :: MIT License
Classifier: Operating System :: OS Independent
Requires-Python: >=3.11.6
License-File: LICENSE
Requires-Dist: et-xmlfile >=1.1.0
Requires-Dist: openpyxl >=3.1.2
Requires-Dist: xlrd >=2.0.1
